trytond/modules/health_surgery_protocols/COPYING
trytond/modules/health_surgery_protocols/README.rst
trytond/modules/health_surgery_protocols/__init__.py
trytond/modules/health_surgery_protocols/data/surgery_protocols.xml
trytond/modules/health_surgery_protocols/health_surgery_protocols.py
trytond/modules/health_surgery_protocols/locale/ar.po
trytond/modules/health_surgery_protocols/locale/de.po
trytond/modules/health_surgery_protocols/locale/el.po
trytond/modules/health_surgery_protocols/locale/eo.po
trytond/modules/health_surgery_protocols/locale/es.po
trytond/modules/health_surgery_protocols/locale/fr.po
trytond/modules/health_surgery_protocols/locale/health_surgery_protocols.pot
trytond/modules/health_surgery_protocols/locale/it_IT.po
trytond/modules/health_surgery_protocols/locale/ja_JP.po
trytond/modules/health_surgery_protocols/locale/ka.po
trytond/modules/health_surgery_protocols/locale/lo.po
trytond/modules/health_surgery_protocols/locale/pt_BR.po
trytond/modules/health_surgery_protocols/locale/sv.po
trytond/modules/health_surgery_protocols/locale/tr.po
trytond/modules/health_surgery_protocols/locale/uk.po
trytond/modules/health_surgery_protocols/locale/zh_CN.po
trytond/modules/health_surgery_protocols/pyproject.toml
trytond/modules/health_surgery_protocols/tests/__init__.py
trytond/modules/health_surgery_protocols/tests/test_health_surgery_protocols.py
trytond/modules/health_surgery_protocols/tryton.cfg
gnuhealth_surgery_protocols-5.0.2.dist-info/METADATA
gnuhealth_surgery_protocols-5.0.2.dist-info/WHEEL
gnuhealth_surgery_protocols-5.0.2.dist-info/licenses/COPYING
gnuhealth_surgery_protocols-5.0.2.dist-info/RECORD
